jtech_dev_checker/__init__.py
jtech_dev_checker/ai_processor.py
jtech_dev_checker/cli.py
jtech_dev_checker/git_diff.py
jtech_dev_checker/pdf_reader.py
jtech_dev_checker/pre_commit_integration.py
jtech_dev_checker-0.1.1.dist-info/METADATA
jtech_dev_checker-0.1.1.dist-info/WHEEL
jtech_dev_checker-0.1.1.dist-info/RECORD
